bisect_scanner/__init__.py
bisect_scanner/__main__.py
bisect_scanner/base_scanner.py
bisect_scanner/config.py
bisect_scanner/example_data.py
bisect_scanner/plot.py
bisect_scanner/scanner.py
bisect_scanner/util.py
bisect_scanner/version.py
bisect_scanner/w3_scanner.py
scripts/__init__.py
scripts/cov.py
scripts/publish.py
bisect_scanner-0.2.5.dist-info/LICENSE
bisect_scanner-0.2.5.dist-info/METADATA
bisect_scanner-0.2.5.dist-info/WHEEL
bisect_scanner-0.2.5.dist-info/top_level.txt
bisect_scanner-0.2.5.dist-info/RECORD
