Metadata-Version: 2.1
Name: bisect-scanner
Version: 0.2.5
Summary: Scan for balance history
Home-page: https://github.com/Gaunt/bisect_scanner
Author: Karel Novak
Author-email: novakk5@gmail.com
License: MIT
Platform: UNKNOWN
Classifier: Development Status :: 4 - Beta
Classifier: License :: OSI Approved :: MIT License
Classifier: Programming Language :: Python :: 3.8
Classifier: Programming Language :: Python :: 3.9
Classifier: Programming Language :: Python :: 3.10
Requires-Dist: web3
Requires-Dist: more-itertools
Requires-Dist: python-dotenv
